<?xml version="1.0" encoding="UTF-8"?>
<objects serializationModel="Studio.02.00.00">
	<object class="MixerReturn" id="{92d37046-f79d-4917-b002-206d0a0bf1dd}">
		<property name="overridingInputFormat">
			<value>2</value>
		</property>
		<property name="inputFormatOverridden">
			<value>true</value>
		</property>
		<property name="name">
			<value>Reverb</value>
		</property>
		<relationship name="effectChain">
			<destination>{3e214743-9e0b-4e52-bc00-7948a294bf7f}</destination>
		</relationship>
		<relationship name="panner">
			<destination>{95cb1b5c-ac76-4738-86ff-148f6d7c740c}</destination>
		</relationship>
		<relationship name="output">
			<destination>{ef91afda-d08c-41c2-ad12-222fa62b39b9}</destination>
		</relationship>
	</object>
	<object class="MixerBusEffectChain" id="{3e214743-9e0b-4e52-bc00-7948a294bf7f}">
		<relationship name="effects">
			<destination>{21d56b75-5274-4de9-ac04-9a67cc3e779b}</destination>
			<destination>{85c04bca-c778-4653-b7e0-4314356362d7}</destination>
		</relationship>
	</object>
	<object class="MixerBusPanner" id="{95cb1b5c-ac76-4738-86ff-148f6d7c740c}" />
	<object class="SFXReverbEffect" id="{21d56b75-5274-4de9-ac04-9a67cc3e779b}">
		<property name="wetLevel">
			<value>0</value>
		</property>
		<property name="dryLevel">
			<value>-80</value>
		</property>
	</object>
	<object class="MixerBusFader" id="{85c04bca-c778-4653-b7e0-4314356362d7}" />
</objects>
